LICENSE
MANIFEST.in
README.rst
setup.cfg
setup.py
phabricator/__init__.py
phabricator/interfaces.json
phabricator3.egg-info/PKG-INFO
phabricator3.egg-info/SOURCES.txt
phabricator3.egg-info/dependency_links.txt
phabricator3.egg-info/not-zip-safe
phabricator3.egg-info/top_level.txt