Metadata-Version: 1.1
Name: phabricator3
Version: 0.1.0
Summary: Phabricator API Bindings
Home-page: http://github.com/konvexum/python-phabricator
Author: Konvexum
Author-email: info@konvexum.se
License: UNKNOWN
Platform: UNKNOWN
Classifier: Intended Audience :: Developers
Classifier: Intended Audience :: System Administrators
Classifier: Operating System :: OS Independent
Classifier: Topic :: Software Development
Classifier: Programming Language :: Python :: 3
Classifier: Programming Language :: Python :: 3.4
